README.rst
setup.py
pysensorbee/__init__.py
pysensorbee/_version.py
pysensorbee/api.py
pysensorbee/cli.py
pysensorbee/tools/__init__.py
pysensorbee/tools/dot.py
pysensorbee/tools/peeker.py
pysensorbee/tools/spider.py
pysensorbee/tools/top.py
sensorbee_python.egg-info/PKG-INFO
sensorbee_python.egg-info/SOURCES.txt
sensorbee_python.egg-info/dependency_links.txt
sensorbee_python.egg-info/entry_points.txt
sensorbee_python.egg-info/requires.txt
sensorbee_python.egg-info/top_level.txt