Metadata-Version: 1.1
Name: sensorbee-python
Version: 0.3.1
Summary: SensorBee API Client
Home-page: https://github.com/kmaehashi/sensorbee-python
Author: Kenichi Maehashi
Author-email: webmaster@kenichimaehashi.com
License: MIT
Platform: UNKNOWN
Classifier: Programming Language :: Python
Classifier: Programming Language :: Python :: 2
Classifier: Programming Language :: Python :: 2.6
Classifier: Programming Language :: Python :: 2.7
Classifier: Programming Language :: Python :: 3
Classifier: Programming Language :: Python :: 3.3
Classifier: Programming Language :: Python :: 3.4
Classifier: Programming Language :: Python :: 3.5
